zaishiyishihejidatabase/__init__.py
zaishiyishihejidatabase/__main__.py
zaishiyishihejidatabase/_template.py
zaishiyishihejidatabase/app.py
zaishiyishihejidatabase/database.py
zaishiyishihejidatabase/db.sqlite3
zaishiyishihejidatabase/favicon.ico
zaishiyishihejidatabase/templates.py
zaishiyishihejidatabase-0.0.1.dist-info/licenses/LICENSE
zaishiyishihejidatabase-0.0.1.dist-info/METADATA
zaishiyishihejidatabase-0.0.1.dist-info/WHEEL
zaishiyishihejidatabase-0.0.1.dist-info/top_level.txt
zaishiyishihejidatabase-0.0.1.dist-info/RECORD
