Metadata-Version: 2.4
Name: zaishiyishihejidatabase
Version: 0.0.1
Summary: 王梓明作品展示页
Home-page: 
Author: 王梓明
Author-email: 1272660211@qq.com
Classifier: Programming Language :: Python :: 3
Classifier: Operating System :: OS Independent
License-File: LICENSE
Requires-Dist: Flask==3.1.2
Requires-Dist: SQLAlchemy==2.0.43
Dynamic: author
Dynamic: author-email
Dynamic: classifier
Dynamic: description
Dynamic: description-content-type
Dynamic: license-file
Dynamic: requires-dist
Dynamic: summary
